[{"test":"bad_to_good_switch","slice":"bad","size":58,"model_rob_large":17.2413793103,"model_rob_small":29.3103448276},{"test":"add_not","slice":"bad","size":58,"model_rob_large":15.5172413793,"model_rob_small":29.3103448276},{"test":"accuracy","slice":"medium","size":401,"model_rob_large":88.2793017456,"model_rob_small":88.2793017456},{"test":"accuracy","slice":"short","size":24,"model_rob_large":91.6666666667,"model_rob_small":91.6666666667},{"test":"accuracy","slice":"total","size":1000,"model_rob_large":88.6,"model_rob_small":88.6}]